AUTHORS.md
CHANGES.md
LICENSE.md
MANIFEST.in
README.md
SSIM_CW-SSIM_comparison.ipynb
setup.cfg
setup.py
pyssim.egg-info/PKG-INFO
pyssim.egg-info/SOURCES.txt
pyssim.egg-info/dependency_links.txt
pyssim.egg-info/entry_points.txt
pyssim.egg-info/requires.txt
pyssim.egg-info/top_level.txt
ssim/__init__.py
ssim/__main__.py
ssim/compat.py
ssim/ssimlib.py
ssim/utils.py
test-images/test1-1.png
test-images/test1-2.png
test-images/test2-1.png
test-images/test2-2.png
test-images/test3-cro.jpg
test-images/test3-lig.jpg
test-images/test3-orig.jpg
test-images/test3-rot.jpg