Metadata-Version: 2.1
Name: pyssim
Version: 0.7
Summary: Module for computing Structured Similarity Image Metric (SSIM) in Python
Home-page: https://github.com/jterrace/pyssim
Author: Antoine Vacavant, Christopher Godfrey, Jeff Terrace
Author-email: jterrace@gmail.com
License: MIT License
Platform: any
License-File: LICENSE.md
License-File: AUTHORS.md
